[
  {
    "code": "E001",
    "name": "University of Visvesvaraya College of Engineering Bangalore ( PUBLIC UNIV. )",
    "city": "Bangalore",
    "type": "Government",
    "lat": 12.981,
    "lng": 77.5936,
    "website": "https://uvce.ac.in",
    "nirf_rank": 63,
    "affiliation": "VTU"
  },
  {
    "code": "E002",
    "name": "Govt.S K S J T Institute of Engineering",
    "city": "Bangalore",
    "type": "Government",
    "lat": 12.9702,
    "lng": 77.5876,
    "website": "https://sksjti.ac.in",
    "nirf_rank": null,
    "affiliation": "VTU"
  },
  {
    "code": "E003",
    "name": "B M S College of Engineering Basavanagudi",
    "city": "Bangalore",
    "type": "Private",
    "lat": 12.9724,
    "lng": 77.589,
    "website": "https://bmsce.ac.in",
    "nirf_rank": 28,
    "affiliation": "VTU"
  },
  {
    "code": "E004",
    "name": "Dr. Ambedkar Institute of Technology",
    "city": "Bangalore",
    "type": "Private",
    "lat": 12.973,
    "lng": 77.5868,
    "website": "https://drait.edu.in",
    "nirf_rank": null,
    "affiliation": "VTU"
  },
  {
    "code": "E005",
    "name": "R. V. College of Engineering",
    "city": "Bangalore",
    "type": "Private",
    "lat": 12.9638,
    "lng": 77.5952,
    "website": "https://rvce.edu.in",
    "nirf_rank": 13,
    "affiliation": "VTU"
  },
  {
    "code": "E006",
    "name": "M S Ramaiah Institute of Technology",
    "city": "Bangalore",
    "type": "Private",
    "lat": 12.9712,
    "lng": 77.5988,
    "website": "https://msrit.edu",
    "nirf_rank": 20,
    "affiliation": "VTU"
  },
  {
    "code": "E007",
    "name": "Dayananda Sagar College of Engineering",
    "city": "Bangalore",
    "type": "Private",
    "lat": 12.9728,
    "lng": 77.595,
    "website": "https://dsce.edu.in",
    "nirf_rank": 85,
    "affiliation": "VTU"
  },
  {
    "code": "E008",
    "name": "Bangalore Institute of Technology",
    "city": "Bangalore",
    "type": "Private",
    "lat": 12.9616,
    "lng": 77.5978,
    "website": "https://bit-bangalore.edu.in",
    "nirf_rank": null,
    "affiliation": "VTU"
  },
  {
    "code": "E009",
    "name": "P E S University (Ring Road Campus)",
    "city": "Bangalore",
    "type": "Private",
    "lat": 12.9688,
    "lng": 77.603,
    "website": "https://pes.edu",
    "nirf_rank": 55,
    "affiliation": "Autonomous"
  },
  {
    "code": "E011",
    "name": "M V J College of Engineering",
    "city": "Bangalore",
    "type": "Private",
    "lat": 12.9806,
    "lng": 77.596,
    "website": "https://mvjce.edu.in",
    "nirf_rank": null,
    "affiliation": "VTU"
  },
  {
    "code": "E012",
    "name": "Sir M.Visveswaraya Institute of Technology Hunasemaranahalli",
    "city": "Bangalore",
    "type": "Private",
    "lat": 12.97,
    "lng": 77.5928,
    "website": "https://smvitm.ac.in",
    "nirf_rank": null,
    "affiliation": "VTU"
  },
  {
    "code": "E013",
    "name": "Ghousia Engineering College",
    "city": "Bangalore",
    "type": "Private",
    "lat": 12.9756,
    "lng": 77.5886,
    "website": "https://ghousia.edu.in",
    "nirf_rank": null,
    "affiliation": "VTU"
  },
  {
    "code": "E014",
    "name": "S J C Institute of Technology",
    "city": "Chikkaballapur",
    "type": "Private",
    "lat": 13.4407,
    "lng": 77.7221,
    "website": "https://sjcit.ac.in",
    "nirf_rank": null,
    "affiliation": "VTU"
  },
  {
    "code": "E015",
    "name": "Dr.T.Thimmaiah Institute of Technology",
    "city": "Kolar",
    "type": "Private",
    "lat": 13.1315,
    "lng": 78.1372,
    "website": "https://ttit.ac.in",
    "nirf_rank": null,
    "affiliation": "VTU"
  },
  {
    "code": "E016",
    "name": "Siddaganga Institute of Technology",
    "city": "Tumkur",
    "type": "Private",
    "lat": 13.3451,
    "lng": 77.1075,
    "website": "https://sit.ac.in",
    "nirf_rank": 120,
    "affiliation": "VTU"
  },
  {
    "code": "E017",
    "name": "Sri Siddhartha Institute of Technology MARALUR",
    "city": "Tumkur",
    "type": "Private",
    "lat": 13.3289,
    "lng": 77.1135,
    "website": "https://ssit.edu.in",
    "nirf_rank": null,
    "affiliation": "VTU"
  },
  {
    "code": "E018",
    "name": "Kalpatharu Institute of Technology",
    "city": "Hassan",
    "type": "Private",
    "lat": 13.0131,
    "lng": 76.1036,
    "website": "https://kit.ac.in",
    "nirf_rank": null,
    "affiliation": "VTU"
  },
  {
    "code": "E021",
    "name": "Sri Jayachamarajendra College of Engineering",
    "city": "Karnataka",
    "type": "Private",
    "lat": 15.3125,
    "lng": 75.7197,
    "website": "https://sjce.ac.in",
    "nirf_rank": 95,
    "affiliation": "VTU"
  },
  {
    "code": "E022",
    "name": "The National Institute of Engineering",
    "city": "Karnataka",
    "type": "Private",
    "lat": 15.3225,
    "lng": 75.7145,
    "website": "https://nie.ac.in",
    "nirf_rank": 110,
    "affiliation": "VTU"
  },
  {
    "code": "E023",
    "name": "P E S College of Engineering",
    "city": "Mandya",
    "type": "Private",
    "lat": 12.5212,
    "lng": 76.8937,
    "website": "https://pescemandya.org",
    "nirf_rank": null,
    "affiliation": "VTU"
  },
  {
    "code": "E024",
    "name": "Malnad College of Engineering",
    "city": "Hassan",
    "type": "Private",
    "lat": 13.0101,
    "lng": 76.0942,
    "website": "https://gsssietumkur.ac.in",
    "nirf_rank": null,
    "affiliation": "VTU"
  },
  {
    "code": "E028",
    "name": "Tontadarya College of Engineering",
    "city": "Gadag",
    "type": "Private",
    "lat": 15.4092,
    "lng": 75.6172,
    "website": "https://drcet.ac.in",
    "nirf_rank": null,
    "affiliation": "VTU"
  },
  {
    "code": "E029",
    "name": "Maratha Mandal Engineering College",
    "city": "Belgaum",
    "type": "Private",
    "lat": 15.8487,
    "lng": 74.5063,
    "website": "https://hkbkce.ac.in",
    "nirf_rank": null,
    "affiliation": "VTU"
  },
  {
    "code": "E031",
    "name": "Basaveshwara Engineering College Bagalkot",
    "city": "Bagalkot",
    "type": "Private",
    "lat": 16.1761,
    "lng": 75.6976,
    "website": "https://bmsce.ac.in",
    "nirf_rank": null,
    "affiliation": "VTU"
  },
  {
    "code": "E032",
    "name": "R.T.E. Soceity's Rural Engineering College",
    "city": "Gadag",
    "type": "Private",
    "lat": 15.4152,
    "lng": 75.6242,
    "website": "https://acharya.ac.in",
    "nirf_rank": null,
    "affiliation": "VTU"
  },
  {
    "code": "E033",
    "name": "Sri Taralabalu Jagadguru Institute of Technology",
    "city": "Ranebennur",
    "type": "Private",
    "lat": 15.3099,
    "lng": 75.7077,
    "website": "https://aceit.ac.in",
    "nirf_rank": null,
    "affiliation": "VTU"
  },
  {
    "code": "E034",
    "name": "Sri Dharmasthala Manjunatheswara College of Engineering",
    "city": "Dharwad",
    "type": "Private",
    "lat": 15.4671,
    "lng": 75.014,
    "website": "https://ait.edu",
    "nirf_rank": null,
    "affiliation": "VTU"
  },
  {
    "code": "E035",
    "name": "Anjuman Institute of Technology & Management",
    "city": "Bhatkal",
    "type": "Private",
    "lat": 15.3187,
    "lng": 75.7133,
    "website": "https://bmsit.net",
    "nirf_rank": null,
    "affiliation": "VTU"
  },
  {
    "code": "E036",
    "name": "KLE Technological University(Formerly KLE Dr.MS Sheshagiri Col.)",
    "city": "Belgaum",
    "type": "Private",
    "lat": 15.8477,
    "lng": 74.4943,
    "website": "https://btlitb.ac.in",
    "nirf_rank": null,
    "affiliation": "VTU"
  },
  {
    "code": "E037",
    "name": "K.L.S. Gogte Institute of Technology",
    "city": "Belgaum",
    "type": "Private",
    "lat": 15.8411,
    "lng": 74.4903,
    "website": "https://cambridge.edu.in",
    "nirf_rank": null,
    "affiliation": "VTU"
  },
  {
    "code": "E038",
    "name": "BLDEA's VP. Dr.P.G. Hallakatti College of Engineering & Technology",
    "city": "Bijapur",
    "type": "Private",
    "lat": 16.831,
    "lng": 75.7024,
    "website": "https://christuniversity.in",
    "nirf_rank": null,
    "affiliation": "VTU"
  },
  {
    "code": "E040",
    "name": "Hira Sugar Institute of Technology",
    "city": "Belgaum",
    "type": "Private",
    "lat": 15.8487,
    "lng": 74.4997,
    "website": "https://dsce.edu.in",
    "nirf_rank": null,
    "affiliation": "VTU"
  },
  {
    "code": "E041",
    "name": "P D A College of Engineering",
    "city": "Gulbarga",
    "type": "Private",
    "lat": 17.3395,
    "lng": 76.8369,
    "website": "https://dsatm.edu.in",
    "nirf_rank": null,
    "affiliation": "VTU"
  },
  {
    "code": "E042",
    "name": "Khaja Banda Nawaz University Kalburgi",
    "city": "Karnataka",
    "type": "Private",
    "lat": 15.3249,
    "lng": 75.7071,
    "website": "https://eastpoint.ac.in",
    "nirf_rank": null,
    "affiliation": "VTU"
  },
  {
    "code": "E043",
    "name": "Gurunanak Dev Engineering College",
    "city": "Bidar",
    "type": "Private",
    "lat": 17.9134,
    "lng": 77.5213,
    "website": "https://ewit.edu.in",
    "nirf_rank": null,
    "affiliation": "VTU"
  },
  {
    "code": "E044",
    "name": "Bheemanna Khandre Institute of Technology Bhalki",
    "city": "Karnataka",
    "type": "Private",
    "lat": 15.3229,
    "lng": 75.7179,
    "website": "https://gfgc.kar.nic.in",
    "nirf_rank": null,
    "affiliation": "VTU"
  },
  {
    "code": "E045",
    "name": "Rao Bahadur Y.Mahabaleswarappa Engineering College Bellari",
    "city": "Karnataka",
    "type": "Private",
    "lat": 15.3209,
    "lng": 75.7099,
    "website": "https://globalacademy.ac.in",
    "nirf_rank": null,
    "affiliation": "VTU"
  },
  {
    "code": "E046",
    "name": "H K E's Society's Sir M Visvesvaraya College of Engineering",
    "city": "Raichur",
    "type": "Private",
    "lat": 16.2058,
    "lng": 77.3493,
    "website": "https://hmsit.ac.in",
    "nirf_rank": null,
    "affiliation": "VTU"
  },
  {
    "code": "E047",
    "name": "Malnad College of Engineering",
    "city": "Hassan",
    "type": "Private",
    "lat": 13.0111,
    "lng": 76.1032,
    "website": "https://iiitb.ac.in",
    "nirf_rank": 8,
    "affiliation": "Autonomous"
  },
  {
    "code": "E048",
    "name": "B M S College of Engineering Basavanagudi",
    "city": "Bangalore",
    "type": "Private",
    "lat": 12.979,
    "lng": 77.5952,
    "website": "https://iimb.ac.in",
    "nirf_rank": null,
    "affiliation": "VTU"
  },
  {
    "code": "E049",
    "name": "B V V Sangha`s Basaveshwara Engineering College",
    "city": "Bagalkot",
    "type": "Private",
    "lat": 16.1787,
    "lng": 75.7008,
    "website": "https://impact.edu.in",
    "nirf_rank": null,
    "affiliation": "VTU"
  },
  {
    "code": "E054",
    "name": "K V G College of Engineering",
    "city": "Sullia",
    "type": "Private",
    "lat": 15.3121,
    "lng": 75.7185,
    "website": "https://kletech.ac.in",
    "nirf_rank": null,
    "affiliation": "VTU"
  },
  {
    "code": "E055",
    "name": "P A College of Engineering",
    "city": "Mangalore",
    "type": "Private",
    "lat": 12.9129,
    "lng": 74.8474,
    "website": "https://kvgce.ac.in",
    "nirf_rank": null,
    "affiliation": "VTU"
  },
  {
    "code": "E056",
    "name": "The National Institute of Engineering(SOUTH CAMPUS)",
    "city": "Mysore",
    "type": "Private",
    "lat": 12.3012,
    "lng": 76.6474,
    "website": "https://lbrce.ac.in",
    "nirf_rank": null,
    "affiliation": "VTU"
  },
  {
    "code": "E057",
    "name": "JSS Science and Technology University(Formerly SJCE)",
    "city": "Mysore",
    "type": "Private",
    "lat": 12.287,
    "lng": 76.6368,
    "website": "https://mbit.ac.in",
    "nirf_rank": null,
    "affiliation": "VTU"
  },
  {
    "code": "E058",
    "name": "P E S College of Engineering Mandya",
    "city": "Mandya",
    "type": "Private",
    "lat": 12.5212,
    "lng": 76.9043,
    "website": "https://mceit.ac.in",
    "nirf_rank": null,
    "affiliation": "VTU"
  },
  {
    "code": "E059",
    "name": "P D A College of Engineering Gulbarga",
    "city": "Gulbarga",
    "type": "Private",
    "lat": 17.3329,
    "lng": 76.8335,
    "website": "https://mite.ac.in",
    "nirf_rank": null,
    "affiliation": "VTU"
  },
  {
    "code": "E060",
    "name": "Dr. Ambedkar Institute Of Technology Jnanabharathi Campus",
    "city": "Bangalore",
    "type": "Private",
    "lat": 12.975,
    "lng": 77.5894,
    "website": "https://moodlakatte.ac.in",
    "nirf_rank": null,
    "affiliation": "VTU"
  },
  {
    "code": "E061",
    "name": "University B.D.T College of Engineering",
    "city": "Davanagere",
    "type": "Private",
    "lat": 14.462,
    "lng": 75.9172,
    "website": "https://nagarjunacollege.ac.in",
    "nirf_rank": null,
    "affiliation": "VTU"
  },
  {
    "code": "E062",
    "name": "Bapuji Institute of Engineering & Technology",
    "city": "Davangere",
    "type": "Private",
    "lat": 15.3093,
    "lng": 75.7199,
    "website": "https://newhorizedu.in",
    "nirf_rank": null,
    "affiliation": "VTU"
  },
  {
    "code": "E063",
    "name": "S J M Institute of Technology",
    "city": "Chitradurga",
    "type": "Private",
    "lat": 15.3173,
    "lng": 75.7205,
    "website": "https://nitttte.ac.in",
    "nirf_rank": null,
    "affiliation": "VTU"
  },
  {
    "code": "E064",
    "name": "Adhichunchanagiri Institute of Technology",
    "city": "Chikmagalur",
    "type": "Private",
    "lat": 15.3221,
    "lng": 75.7113,
    "website": "https://nmit.ac.in",
    "nirf_rank": null,
    "affiliation": "VTU"
  },
  {
    "code": "E065",
    "name": "Jawaharlal Nehru New College of Engineering",
    "city": "Shimoga",
    "type": "Private",
    "lat": 13.9225,
    "lng": 75.5637,
    "website": "https://nieit.ac.in",
    "nirf_rank": null,
    "affiliation": "VTU"
  },
  {
    "code": "E066",
    "name": "University B.D.T. college of Engineering",
    "city": "Karnataka",
    "type": "Private",
    "lat": 15.3191,
    "lng": 75.7163,
    "website": "https://pes.edu",
    "nirf_rank": null,
    "affiliation": "VTU"
  },
  {
    "code": "E070",
    "name": "Bahubali College of Engineering Hassan Dist",
    "city": "Hassan",
    "type": "Private",
    "lat": 12.9945,
    "lng": 76.1044,
    "website": "https://rnsit.ac.in",
    "nirf_rank": 140,
    "affiliation": "VTU"
  },
  {
    "code": "E071",
    "name": "Vidya Vardhaka College of Engineering Mysuru",
    "city": "Mysore",
    "type": "Private",
    "lat": 12.295,
    "lng": 76.6376,
    "website": "https://rrce.org",
    "nirf_rank": null,
    "affiliation": "VTU"
  },
  {
    "code": "E075",
    "name": "Ballari Institute of Technology and Management Near Allipur Bellary",
    "city": "Bellary",
    "type": "Private",
    "lat": 15.1376,
    "lng": 76.9202,
    "website": "https://seacet.ac.in",
    "nirf_rank": null,
    "affiliation": "VTU"
  },
  {
    "code": "E076",
    "name": "Proudadevaraya Institute of Technology Indiranagar Hospet",
    "city": "Hospet",
    "type": "Private",
    "lat": 15.3151,
    "lng": 75.7143,
    "website": "https://sjbit.edu.in",
    "nirf_rank": null,
    "affiliation": "VTU"
  },
  {
    "code": "E077",
    "name": "Vidya Vikas Institute of Engineering & Technology",
    "city": "Mysore",
    "type": "Private",
    "lat": 12.3028,
    "lng": 76.6458,
    "website": "https://sjem.ac.in",
    "nirf_rank": null,
    "affiliation": "VTU"
  },
  {
    "code": "E078",
    "name": "The Oxford College of Engineering",
    "city": "Bangalore",
    "type": "Private",
    "lat": 12.969,
    "lng": 77.5938,
    "website": "https://skit.ac.in",
    "nirf_rank": null,
    "affiliation": "VTU"
  },
  {
    "code": "E079",
    "name": "Acharya Institute of Technology",
    "city": "Bangalore",
    "type": "Private",
    "lat": 12.969,
    "lng": 77.6016,
    "website": "https://srinivascollege.edu.in",
    "nirf_rank": null,
    "affiliation": "VTU"
  },
  {
    "code": "E081",
    "name": "SRI SIDDHARTHA SCHOOL OF ENGINEERING",
    "city": "Tumkur",
    "type": "Private",
    "lat": 13.3363,
    "lng": 77.1089,
    "website": "https://ssahe.ac.in",
    "nirf_rank": null,
    "affiliation": "VTU"
  },
  {
    "code": "E082",
    "name": "J S S Academy of Technical Education",
    "city": "Bangalore",
    "type": "Private",
    "lat": 12.9756,
    "lng": 77.5858,
    "website": "https://sstit.in",
    "nirf_rank": null,
    "affiliation": "VTU"
  },
  {
    "code": "E083",
    "name": "H.K.B.K.College of Engineering",
    "city": "Bangalore",
    "type": "Private",
    "lat": 12.9722,
    "lng": 77.5892,
    "website": "https://sunriseit.edu.in",
    "nirf_rank": null,
    "affiliation": "VTU"
  },
  {
    "code": "E085",
    "name": "APS College of Engineering Somanahalli",
    "city": "Bangalore",
    "type": "Private",
    "lat": 12.9808,
    "lng": 77.5996,
    "website": "https://tcetmangalore.ac.in",
    "nirf_rank": null,
    "affiliation": "VTU"
  },
  {
    "code": "E086",
    "name": "Sri Sairam College Of Engineering",
    "city": "Bangalore",
    "type": "Private",
    "lat": 12.9726,
    "lng": 77.601,
    "website": "https://toce.ac.in",
    "nirf_rank": null,
    "affiliation": "VTU"
  },
  {
    "code": "E087",
    "name": "Vivekananada Institute of Technology",
    "city": "Bangalore",
    "type": "Private",
    "lat": 12.9714,
    "lng": 77.5886,
    "website": "https://vemana.org",
    "nirf_rank": null,
    "affiliation": "VTU"
  },
  {
    "code": "E088",
    "name": "Bangalore College of Engineering and Technology Chandapura",
    "city": "Bangalore",
    "type": "Private",
    "lat": 12.9648,
    "lng": 77.5918,
    "website": "https://viat.ac.in",
    "nirf_rank": null,
    "affiliation": "VTU"
  },
  {
    "code": "E090",
    "name": "Sri Revana Siddeswara Institute of Technology",
    "city": "Bangalore",
    "type": "Private",
    "lat": 12.9726,
    "lng": 77.586,
    "website": "https://vtu.ac.in",
    "nirf_rank": null,
    "affiliation": "VTU"
  },
  {
    "code": "E091",
    "name": "K S Institute of Technology",
    "city": "Bangalore",
    "type": "Private",
    "lat": 12.9666,
    "lng": 77.6014,
    "website": null,
    "nirf_rank": null,
    "affiliation": "VTU"
  },
  {
    "code": "E092",
    "name": "Vemana Institute of Technology",
    "city": "Bangalore",
    "type": "Private",
    "lat": 12.9684,
    "lng": 77.6042,
    "website": null,
    "nirf_rank": null,
    "affiliation": "VTU"
  },
  {
    "code": "E093",
    "name": "Basavakalyana Engineering College Basavakalyana",
    "city": "Bidar",
    "type": "Private",
    "lat": 17.9134,
    "lng": 77.5191,
    "website": null,
    "nirf_rank": null,
    "affiliation": "VTU"
  },
  {
    "code": "E094",
    "name": "Coorg Institute of Technology",
    "city": "Coorg",
    "type": "Private",
    "lat": 15.3231,
    "lng": 75.7115,
    "website": null,
    "nirf_rank": null,
    "affiliation": "VTU"
  },
  {
    "code": "E095",
    "name": "AMC Engineering College",
    "city": "Bangalore",
    "type": "Private",
    "lat": 12.9748,
    "lng": 77.594,
    "website": null,
    "nirf_rank": null,
    "affiliation": "VTU"
  },
  {
    "code": "E096",
    "name": "East Point College of Engineering & Technology",
    "city": "Bangalore",
    "type": "Private",
    "lat": 12.9682,
    "lng": 77.604,
    "website": null,
    "nirf_rank": null,
    "affiliation": "VTU"
  },
  {
    "code": "E097",
    "name": "C M R Institute of Technology",
    "city": "Bangalore",
    "type": "Private",
    "lat": 12.97,
    "lng": 77.599,
    "website": null,
    "nirf_rank": null,
    "affiliation": "VTU"
  },
  {
    "code": "E098",
    "name": "Atria Institute of Technology",
    "city": "Bangalore",
    "type": "Private",
    "lat": 12.9638,
    "lng": 77.6028,
    "website": null,
    "nirf_rank": null,
    "affiliation": "VTU"
  },
  {
    "code": "E099",
    "name": "New Horizon College of Engineering",
    "city": "Bangalore",
    "type": "Private",
    "lat": 12.9766,
    "lng": 77.589,
    "website": null,
    "nirf_rank": null,
    "affiliation": "VTU"
  },
  {
    "code": "E100",
    "name": "K N S Institute of Technology",
    "city": "Bangalore",
    "type": "Private",
    "lat": 12.9754,
    "lng": 77.6018,
    "website": null,
    "nirf_rank": null,
    "affiliation": "VTU"
  },
  {
    "code": "E101",
    "name": "Channabasaveshwara Institute of Technology",
    "city": "Tumkur",
    "type": "Private",
    "lat": 13.3375,
    "lng": 77.1223,
    "website": null,
    "nirf_rank": null,
    "affiliation": "VTU"
  },
  {
    "code": "E102",
    "name": "DONBOSCO Institute of Technology",
    "city": "Bangalore",
    "type": "Private",
    "lat": 12.9762,
    "lng": 77.6042,
    "website": null,
    "nirf_rank": null,
    "affiliation": "VTU"
  },
  {
    "code": "E103",
    "name": "Global Academy of Technology",
    "city": "Bangalore",
    "type": "Private",
    "lat": 12.9722,
    "lng": 77.5884,
    "website": null,
    "nirf_rank": null,
    "affiliation": "VTU"
  },
  {
    "code": "E104",
    "name": "Nagarjuna College of Engineering & Technology",
    "city": "Bangalore",
    "type": "Private",
    "lat": 12.9762,
    "lng": 77.6002,
    "website": null,
    "nirf_rank": null,
    "affiliation": "VTU"
  },
  {
    "code": "E105",
    "name": "Nitte Meenakshi Institutute of Technology",
    "city": "Bangalore",
    "type": "Private",
    "lat": 12.9782,
    "lng": 77.6028,
    "website": null,
    "nirf_rank": null,
    "affiliation": "VTU"
  },
  {
    "code": "E106",
    "name": "East West Institute Of Technology",
    "city": "Bangalore",
    "type": "Private",
    "lat": 12.963,
    "lng": 77.587,
    "website": null,
    "nirf_rank": null,
    "affiliation": "VTU"
  },
  {
    "code": "E107",
    "name": "B N M Institute of Technology",
    "city": "Bangalore",
    "type": "Private",
    "lat": 12.9634,
    "lng": 77.5892,
    "website": null,
    "nirf_rank": null,
    "affiliation": "VTU"
  },
  {
    "code": "E108",
    "name": "SAPTHAGIRI NPS UNIVERISTY #14/5",
    "city": "Bangaluru",
    "type": "Private",
    "lat": 15.3215,
    "lng": 75.7233,
    "website": null,
    "nirf_rank": null,
    "affiliation": "VTU"
  },
  {
    "code": "E109",
    "name": "City Engineering College",
    "city": "Bangalore",
    "type": "Private",
    "lat": 12.9622,
    "lng": 77.591,
    "website": null,
    "nirf_rank": null,
    "affiliation": "VTU"
  },
  {
    "code": "E111",
    "name": "Sri Venkateshwara College of Engineering",
    "city": "Bangalore",
    "type": "Private",
    "lat": 12.9636,
    "lng": 77.5938,
    "website": null,
    "nirf_rank": null,
    "affiliation": "VTU"
  },
  {
    "code": "E112",
    "name": "Sri Krishna Institute of Technology",
    "city": "Bangalore",
    "type": "Private",
    "lat": 12.9724,
    "lng": 77.5964,
    "website": null,
    "nirf_rank": null,
    "affiliation": "VTU"
  },
  {
    "code": "E113",
    "name": "Sambhram Institute of Technology",
    "city": "Bangalore",
    "type": "Private",
    "lat": 12.9766,
    "lng": 77.5858,
    "website": null,
    "nirf_rank": null,
    "affiliation": "VTU"
  },
  {
    "code": "E114",
    "name": "G M Institute of Technology Davanagere",
    "city": "Davanagere",
    "type": "Private",
    "lat": 14.4714,
    "lng": 75.9282,
    "website": null,
    "nirf_rank": null,
    "affiliation": "VTU"
  },
  {
    "code": "E115",
    "name": "S J B Institute of Technology Kengeri",
    "city": "Bangalore",
    "type": "Private",
    "lat": 12.969,
    "lng": 77.6038,
    "website": null,
    "nirf_rank": null,
    "affiliation": "VTU"
  },
  {
    "code": "E116",
    "name": "R.L.Jalappa Institute of Technology",
    "city": "Bangalore",
    "type": "Private",
    "lat": 12.9734,
    "lng": 77.5878,
    "website": null,
    "nirf_rank": null,
    "affiliation": "VTU"
  },
  {
    "code": "E118",
    "name": "RNS Institute of Technology",
    "city": "Bangalore",
    "type": "Private",
    "lat": 12.9804,
    "lng": 77.5918,
    "website": null,
    "nirf_rank": null,
    "affiliation": "VTU"
  },
  {
    "code": "E119",
    "name": "K C T Engineering College Roza(B)",
    "city": "Gulbarga",
    "type": "Private",
    "lat": 17.3281,
    "lng": 76.8289,
    "website": null,
    "nirf_rank": null,
    "affiliation": "VTU"
  },
  {
    "code": "E120",
    "name": "Jnanavikasa Institute of Technology",
    "city": "Bangalore",
    "type": "Private",
    "lat": 12.9684,
    "lng": 77.603,
    "website": null,
    "nirf_rank": null,
    "affiliation": "VTU"
  },
  {
    "code": "E121",
    "name": "Vivekananada College of Engineering Technology",
    "city": "Dakshina",
    "type": "Private",
    "lat": 15.3169,
    "lng": 75.7155,
    "website": null,
    "nirf_rank": null,
    "affiliation": "VTU"
  },
  {
    "code": "E123",
    "name": "Canara Engineering College Bantwal DK DIST",
    "city": "Karnataka",
    "type": "Private",
    "lat": 15.3167,
    "lng": 75.7051,
    "website": null,
    "nirf_rank": null,
    "affiliation": "VTU"
  },
  {
    "code": "E124",
    "name": "Rajiv Gandhi Institute of Technology",
    "city": "Bangalore",
    "type": "Private",
    "lat": 12.9738,
    "lng": 77.6016,
    "website": null,
    "nirf_rank": null,
    "affiliation": "VTU"
  },
  {
    "code": "E126",
    "name": "B M S Institute of Technology and Management Yelahanka",
    "city": "Bangalore",
    "type": "Private",
    "lat": 12.9672,
    "lng": 77.5848,
    "website": null,
    "nirf_rank": null,
    "affiliation": "VTU"
  },
  {
    "code": "E127",
    "name": "M S Engineering College",
    "city": "Bangalore",
    "type": "Private",
    "lat": 12.9806,
    "lng": 77.5892,
    "website": null,
    "nirf_rank": null,
    "affiliation": "VTU"
  },
  {
    "code": "E128",
    "name": "Sharnbasva University(Formerly Appa Inst. of Tech.) Brahmpur",
    "city": "Gulbarga",
    "type": "Private",
    "lat": 17.3295,
    "lng": 76.8305,
    "website": null,
    "nirf_rank": null,
    "affiliation": "VTU"
  },
  {
    "code": "E129",
    "name": "St.Joseph Engineering College",
    "city": "Mangalore",
    "type": "Private",
    "lat": 12.9233,
    "lng": 74.862,
    "website": null,
    "nirf_rank": null,
    "affiliation": "VTU"
  },
  {
    "code": "E130",
    "name": "Shridevi Institute of Engineering & Technology",
    "city": "Tumkur",
    "type": "Private",
    "lat": 13.3401,
    "lng": 77.1217,
    "website": null,
    "nirf_rank": null,
    "affiliation": "VTU"
  },
  {
    "code": "E132",
    "name": "Secab Institute of Engineering & Technology",
    "city": "Bijapur",
    "type": "Private",
    "lat": 16.8368,
    "lng": 75.713,
    "website": null,
    "nirf_rank": null,
    "affiliation": "VTU"
  },
  {
    "code": "E133",
    "name": "G S S S Institute of Engineering and Technology for Women",
    "city": "Mysore",
    "type": "Private",
    "lat": 12.2964,
    "lng": 76.6358,
    "website": null,
    "nirf_rank": null,
    "affiliation": "VTU"
  },
  {
    "code": "E134",
    "name": "Smt. Kamala & Sri Venkappa M.Agadi College of Engineering & Technology",
    "city": "Gadag",
    "type": "Private",
    "lat": 15.4152,
    "lng": 75.6318,
    "website": null,
    "nirf_rank": null,
    "affiliation": "VTU"
  },
  {
    "code": "E135",
    "name": "K L S Viswanathrao Deshpande Institute of Technology Haliyal",
    "city": "Uttara",
    "type": "Private",
    "lat": 15.3125,
    "lng": 75.7233,
    "website": null,
    "nirf_rank": null,
    "affiliation": "VTU"
  },
  {
    "code": "E136",
    "name": "Moodalakatte Institute of Technology",
    "city": "Udupi",
    "type": "Private",
    "lat": 13.3495,
    "lng": 74.7395,
    "website": null,
    "nirf_rank": null,
    "affiliation": "VTU"
  },
  {
    "code": "E139",
    "name": "Impact College of Engineering & Applied Sciences",
    "city": "Bangalore",
    "type": "Private",
    "lat": 12.9644,
    "lng": 77.6028,
    "website": null,
    "nirf_rank": null,
    "affiliation": "VTU"
  },
  {
    "code": "E141",
    "name": "P E S University (Electronic City Campus)",
    "city": "Bangalore",
    "type": "Private",
    "lat": 12.9716,
    "lng": 77.5918,
    "website": null,
    "nirf_rank": null,
    "affiliation": "VTU"
  },
  {
    "code": "E142",
    "name": "Adhichunchanagiri University",
    "city": "Karnataka",
    "type": "Private",
    "lat": 15.3259,
    "lng": 75.7163,
    "website": null,
    "nirf_rank": null,
    "affiliation": "VTU"
  },
  {
    "code": "E144",
    "name": "Srinivas Institute of Technology",
    "city": "Mangalore",
    "type": "Private",
    "lat": 12.9231,
    "lng": 74.8588,
    "website": null,
    "nirf_rank": null,
    "affiliation": "VTU"
  },
  {
    "code": "E145",
    "name": "Rajarajeswari College of Engineering",
    "city": "Bangalore",
    "type": "Private",
    "lat": 12.9792,
    "lng": 77.5878,
    "website": null,
    "nirf_rank": null,
    "affiliation": "VTU"
  },
  {
    "code": "E146",
    "name": "Shreedevi Institute of Technology",
    "city": "Mangalore",
    "type": "Private",
    "lat": 12.9197,
    "lng": 74.8654,
    "website": null,
    "nirf_rank": null,
    "affiliation": "VTU"
  },
  {
    "code": "E147",
    "name": "T.John Institute of technology",
    "city": "Bangalore",
    "type": "Private",
    "lat": 12.9718,
    "lng": 77.588,
    "website": null,
    "nirf_rank": null,
    "affiliation": "VTU"
  },
  {
    "code": "E149",
    "name": "Cambridge Institutute of Technology",
    "city": "Bangalore",
    "type": "Private",
    "lat": 12.9622,
    "lng": 77.6028,
    "website": null,
    "nirf_rank": null,
    "affiliation": "VTU"
  },
  {
    "code": "E150",
    "name": "P E S Institute of Technology & Management",
    "city": "Shimoga",
    "type": "Private",
    "lat": 13.9345,
    "lng": 75.5647,
    "website": null,
    "nirf_rank": null,
    "affiliation": "VTU"
  },
  {
    "code": "E151",
    "name": "Mangalore Institute of Technology & Engineering",
    "city": "Mangalore",
    "type": "Private",
    "lat": 12.9229,
    "lng": 74.8476,
    "website": null,
    "nirf_rank": null,
    "affiliation": "VTU"
  },
  {
    "code": "E152",
    "name": "S D M Institute of Tech",
    "city": "Dakshina",
    "type": "Private",
    "lat": 15.3189,
    "lng": 75.7153,
    "website": null,
    "nirf_rank": null,
    "affiliation": "VTU"
  },
  {
    "code": "E153",
    "name": "S E A College of Engineering & Technology",
    "city": "Bangalore",
    "type": "Private",
    "lat": 12.9706,
    "lng": 77.5944,
    "website": null,
    "nirf_rank": null,
    "affiliation": "VTU"
  },
  {
    "code": "E154",
    "name": "Government Engineering College",
    "city": "Chamarajanagar",
    "type": "Government",
    "lat": 15.3111,
    "lng": 75.7119,
    "website": null,
    "nirf_rank": null,
    "affiliation": "VTU"
  },
  {
    "code": "E155",
    "name": "Government Engineering College",
    "city": "Hassan",
    "type": "Government",
    "lat": 13.0127,
    "lng": 76.0942,
    "website": null,
    "nirf_rank": null,
    "affiliation": "VTU"
  },
  {
    "code": "E156",
    "name": "K R PET KRISHNA",
    "city": "Mandya",
    "type": "Government",
    "lat": 12.5276,
    "lng": 76.8855,
    "website": null,
    "nirf_rank": null,
    "affiliation": "VTU"
  },
  {
    "code": "E157",
    "name": "Government Engineering College",
    "city": "Ramanagara",
    "type": "Government",
    "lat": 12.7117,
    "lng": 77.2856,
    "website": null,
    "nirf_rank": null,
    "affiliation": "VTU"
  },
  {
    "code": "E158",
    "name": "Maharaja Institute of Technology Mysore",
    "city": "Mysore",
    "type": "Private",
    "lat": 12.3016,
    "lng": 76.6374,
    "website": null,
    "nirf_rank": null,
    "affiliation": "VTU"
  },
  {
    "code": "E159",
    "name": "Karavali Institute of Technology",
    "city": "Mangalore",
    "type": "Private",
    "lat": 12.9145,
    "lng": 74.8606,
    "website": null,
    "nirf_rank": null,
    "affiliation": "VTU"
  },
  {
    "code": "E160",
    "name": "Sahyadri College of Engg. and Management",
    "city": "Mangalore",
    "type": "Private",
    "lat": 12.9049,
    "lng": 74.8554,
    "website": null,
    "nirf_rank": null,
    "affiliation": "VTU"
  },
  {
    "code": "E161",
    "name": "Government Engineering College",
    "city": "Kushalanagar",
    "type": "Government",
    "lat": 15.3241,
    "lng": 75.7223,
    "website": null,
    "nirf_rank": null,
    "affiliation": "VTU"
  },
  {
    "code": "E162",
    "name": "Government Engineering College",
    "city": "Raichur",
    "type": "Government",
    "lat": 16.214,
    "lng": 77.3483,
    "website": null,
    "nirf_rank": null,
    "affiliation": "VTU"
  },
  {
    "code": "E163",
    "name": "Government Engineering College",
    "city": "Haveri",
    "type": "Government",
    "lat": 15.3089,
    "lng": 75.7193,
    "website": null,
    "nirf_rank": null,
    "affiliation": "VTU"
  },
  {
    "code": "E164",
    "name": "Government Engineering College",
    "city": "Karnataka",
    "type": "Government",
    "lat": 15.3119,
    "lng": 75.7225,
    "website": null,
    "nirf_rank": null,
    "affiliation": "VTU"
  },
  {
    "code": "E165",
    "name": "Yenepoya Institute Of Technology",
    "city": "Mangalore",
    "type": "Private",
    "lat": 12.9225,
    "lng": 74.846,
    "website": null,
    "nirf_rank": null,
    "affiliation": "VTU"
  },
  {
    "code": "E166",
    "name": "K L E Institute of Technology",
    "city": "Hubli",
    "type": "Private",
    "lat": 15.3561,
    "lng": 75.1304,
    "website": null,
    "nirf_rank": null,
    "affiliation": "VTU"
  },
  {
    "code": "E167",
    "name": "K L E Ss K L E College of Engineering and Technology Chikkodi",
    "city": "Belgaum",
    "type": "Private",
    "lat": 15.8479,
    "lng": 74.4963,
    "website": null,
    "nirf_rank": null,
    "affiliation": "VTU"
  },
  {
    "code": "E168",
    "name": "Amrutha Institute of Engineering & Management Science",
    "city": "Karnataka",
    "type": "Private",
    "lat": 15.3147,
    "lng": 75.7127,
    "website": null,
    "nirf_rank": null,
    "affiliation": "VTU"
  },
  {
    "code": "E169",
    "name": "Alva's Institute of Engineering & Technology",
    "city": "Karnataka",
    "type": "Private",
    "lat": 15.3073,
    "lng": 75.7085,
    "website": null,
    "nirf_rank": null,
    "affiliation": "VTU"
  },
  {
    "code": "E171",
    "name": "Brindavan College of Engineering",
    "city": "Bangalore",
    "type": "Private",
    "lat": 12.98,
    "lng": 77.599,
    "website": null,
    "nirf_rank": null,
    "affiliation": "VTU"
  },
  {
    "code": "E172",
    "name": "R.R. Institute of Technology",
    "city": "Bangalore",
    "type": "Private",
    "lat": 12.9814,
    "lng": 77.597,
    "website": null,
    "nirf_rank": null,
    "affiliation": "VTU"
  },
  {
    "code": "E173",
    "name": "Sai Vidya Institute of Technology",
    "city": "Bangalore",
    "type": "Private",
    "lat": 12.9718,
    "lng": 77.6,
    "website": null,
    "nirf_rank": null,
    "affiliation": "VTU"
  },
  {
    "code": "E174",
    "name": "Dr. Sri Sri Sri Shivakumara Mahaswamyji College of Engineering",
    "city": "Bangalore",
    "type": "Private",
    "lat": 12.9676,
    "lng": 77.5868,
    "website": null,
    "nirf_rank": null,
    "affiliation": "VTU"
  },
  {
    "code": "E175",
    "name": "S.S.E.T.S.S.G.Balekundri Institute of Technology",
    "city": "Belgaum",
    "type": "Private",
    "lat": 15.8551,
    "lng": 74.4909,
    "website": null,
    "nirf_rank": null,
    "affiliation": "VTU"
  },
  {
    "code": "E176",
    "name": "Navodaya Institute of Technology",
    "city": "Raichur",
    "type": "Private",
    "lat": 16.213,
    "lng": 77.3361,
    "website": null,
    "nirf_rank": null,
    "affiliation": "VTU"
  },
  {
    "code": "E177",
    "name": "Rajeev Institute of Technology",
    "city": "Hassan",
    "type": "Private",
    "lat": 13.0063,
    "lng": 76.0922,
    "website": null,
    "nirf_rank": null,
    "affiliation": "VTU"
  },
  {
    "code": "E178",
    "name": "The National Institute of Engineering(NORTH CAMPUS)",
    "city": "Mysore",
    "type": "Private",
    "lat": 12.297,
    "lng": 76.6484,
    "website": null,
    "nirf_rank": null,
    "affiliation": "VTU"
  },
  {
    "code": "E180",
    "name": "Beary's Institute of Technology",
    "city": "Mangalore",
    "type": "Private",
    "lat": 12.9145,
    "lng": 74.8494,
    "website": null,
    "nirf_rank": null,
    "affiliation": "VTU"
  },
  {
    "code": "E181",
    "name": "Sri Basaveswara Institute of Technology",
    "city": "Tiptur",
    "type": "Private",
    "lat": 13.2528,
    "lng": 76.4723,
    "website": null,
    "nirf_rank": null,
    "affiliation": "VTU"
  },
  {
    "code": "E183",
    "name": "Sha-Shib College of Engineering Chickballapur",
    "city": "Karnataka",
    "type": "Private",
    "lat": 15.3173,
    "lng": 75.7097,
    "website": null,
    "nirf_rank": null,
    "affiliation": "VTU"
  },
  {
    "code": "E184",
    "name": "C Byre Gowda Institute of Technology",
    "city": "Kolar",
    "type": "Private",
    "lat": 13.1433,
    "lng": 78.1346,
    "website": null,
    "nirf_rank": null,
    "affiliation": "VTU"
  },
  {
    "code": "E185",
    "name": "Angadi Institute of Technology and Management",
    "city": "Belgaum",
    "type": "Private",
    "lat": 15.8443,
    "lng": 74.4987,
    "website": null,
    "nirf_rank": null,
    "affiliation": "VTU"
  },
  {
    "code": "E186",
    "name": "ACS College of Engineering",
    "city": "Bangalore",
    "type": "Private",
    "lat": 12.9812,
    "lng": 77.6026,
    "website": null,
    "nirf_rank": null,
    "affiliation": "VTU"
  },
  {
    "code": "E188",
    "name": "Vijaya Vittala Institute of Technology",
    "city": "Bangalore",
    "type": "Private",
    "lat": 12.9682,
    "lng": 77.5848,
    "website": null,
    "nirf_rank": null,
    "affiliation": "VTU"
  },
  {
    "code": "E189",
    "name": "NAVKIS COLLEGE OF ENGINEERING",
    "city": "Hassan",
    "type": "Private",
    "lat": 13.0111,
    "lng": 76.1096,
    "website": null,
    "nirf_rank": null,
    "affiliation": "VTU"
  },
  {
    "code": "E190",
    "name": "Acharya N R V School of Architecture Hesarghatta Main Road Banglore",
    "city": "Karnataka",
    "type": "Private",
    "lat": 15.3173,
    "lng": 75.7065,
    "website": null,
    "nirf_rank": null,
    "affiliation": "VTU"
  },
  {
    "code": "E191",
    "name": "Akshaya Institute of Technology",
    "city": "Tumkur",
    "type": "Private",
    "lat": 13.3337,
    "lng": 77.1219,
    "website": null,
    "nirf_rank": null,
    "affiliation": "VTU"
  },
  {
    "code": "E193",
    "name": "Srinivas University SRINIVAS CAMPUS MUKKA MANGALURU",
    "city": "Mangalore",
    "type": "Private",
    "lat": 12.9081,
    "lng": 74.8586,
    "website": null,
    "nirf_rank": null,
    "affiliation": "VTU"
  },
  {
    "code": "E194",
    "name": "Government Engineering College",
    "city": "Karwar",
    "type": "Government",
    "lat": 14.7947,
    "lng": 74.1202,
    "website": null,
    "nirf_rank": null,
    "affiliation": "VTU"
  },
  {
    "code": "E196",
    "name": "Jain College of Engineering",
    "city": "Belgaum",
    "type": "Private",
    "lat": 15.8439,
    "lng": 74.5023,
    "website": null,
    "nirf_rank": null,
    "affiliation": "VTU"
  },
  {
    "code": "E197",
    "name": "Veerappa Nisty Engineering College",
    "city": "Yadgir",
    "type": "Private",
    "lat": 16.774,
    "lng": 77.1319,
    "website": null,
    "nirf_rank": null,
    "affiliation": "VTU"
  },
  {
    "code": "E198",
    "name": "Sharnbasva University College for Women(Formerly Godutai) Gulbarga",
    "city": "Gulbarga",
    "type": "Private",
    "lat": 17.3263,
    "lng": 76.8425,
    "website": null,
    "nirf_rank": null,
    "affiliation": "VTU"
  },
  {
    "code": "E199",
    "name": "AGM Rural Engineering College",
    "city": "Hubli",
    "type": "Private",
    "lat": 15.3641,
    "lng": 75.1254,
    "website": null,
    "nirf_rank": null,
    "affiliation": "VTU"
  },
  {
    "code": "E201",
    "name": "Gopalan College of Engineering & Management",
    "city": "Bangalore",
    "type": "Private",
    "lat": 12.9722,
    "lng": 77.5988,
    "website": null,
    "nirf_rank": null,
    "affiliation": "VTU"
  },
  {
    "code": "E202",
    "name": "Sampoorna Group of Institutions",
    "city": "Ramanagara",
    "type": "Private",
    "lat": 12.7117,
    "lng": 77.2894,
    "website": null,
    "nirf_rank": null,
    "affiliation": "VTU"
  },
  {
    "code": "E203",
    "name": "K S School of Engineering & Management",
    "city": "Bangalore",
    "type": "Private",
    "lat": 12.9652,
    "lng": 77.5878,
    "website": null,
    "nirf_rank": null,
    "affiliation": "VTU"
  },
  {
    "code": "E204",
    "name": "Bangalore Technological Institute",
    "city": "Bangalore",
    "type": "Private",
    "lat": 12.9746,
    "lng": 77.586,
    "website": null,
    "nirf_rank": null,
    "affiliation": "VTU"
  },
  {
    "code": "E205",
    "name": "ATME College of Engineering",
    "city": "Mysore",
    "type": "Private",
    "lat": 12.2966,
    "lng": 76.6408,
    "website": null,
    "nirf_rank": null,
    "affiliation": "VTU"
  },
  {
    "code": "E206",
    "name": "Shri Madhwa Vadiraja Institute of Technology and Management",
    "city": "Udupi",
    "type": "Private",
    "lat": 13.3481,
    "lng": 74.7453,
    "website": null,
    "nirf_rank": null,
    "affiliation": "VTU"
  },
  {
    "code": "E207",
    "name": "V S M`s Somashekhar R Kothiwale Institute of Technology",
    "city": "Belgaum",
    "type": "Private",
    "lat": 15.8557,
    "lng": 74.5001,
    "website": null,
    "nirf_rank": null,
    "affiliation": "VTU"
  },
  {
    "code": "E208",
    "name": "Achutha Institute of Technology",
    "city": "Bangalore",
    "type": "Private",
    "lat": 12.9772,
    "lng": 77.586,
    "website": null,
    "nirf_rank": null,
    "affiliation": "VTU"
  },
  {
    "code": "E209",
    "name": "Jyothi Institute of Technology",
    "city": "Bangalore",
    "type": "Private",
    "lat": 12.9714,
    "lng": 77.5932,
    "website": null,
    "nirf_rank": null,
    "affiliation": "VTU"
  },
  {
    "code": "E210",
    "name": "G Madegowda Institute of Technology",
    "city": "Mandya",
    "type": "Private",
    "lat": 12.522,
    "lng": 76.8931,
    "website": null,
    "nirf_rank": null,
    "affiliation": "VTU"
  },
  {
    "code": "E211",
    "name": "Jain Institute of Technology",
    "city": "Davanagere",
    "type": "Private",
    "lat": 14.4612,
    "lng": 75.921,
    "website": null,
    "nirf_rank": null,
    "affiliation": "VTU"
  },
  {
    "code": "E212",
    "name": "Dayananda Sagar Academy of Technology Kanakapur Main Road",
    "city": "Bangalore",
    "type": "Private",
    "lat": 12.969,
    "lng": 77.5852,
    "website": null,
    "nirf_rank": null,
    "affiliation": "VTU"
  },
  {
    "code": "E213",
    "name": "Lingarajappa Engineering College",
    "city": "Bidar",
    "type": "Private",
    "lat": 17.9076,
    "lng": 77.5179,
    "website": null,
    "nirf_rank": null,
    "affiliation": "VTU"
  },
  {
    "code": "E215",
    "name": "B M S School of Architecture Yalahanka",
    "city": "Bangalore",
    "type": "Private",
    "lat": 12.9654,
    "lng": 77.6026,
    "website": null,
    "nirf_rank": null,
    "affiliation": "VTU"
  },
  {
    "code": "E216",
    "name": "Shetty Institute of Technology",
    "city": "Gulbarga",
    "type": "Private",
    "lat": 17.3283,
    "lng": 76.8255,
    "website": null,
    "nirf_rank": null,
    "affiliation": "VTU"
  },
  {
    "code": "E220",
    "name": "ALLIANCE University Central Campus",
    "city": "Bangalore",
    "type": "Private",
    "lat": 12.9644,
    "lng": 77.6016,
    "website": null,
    "nirf_rank": null,
    "affiliation": "VTU"
  },
  {
    "code": "E221",
    "name": "Biluru Gurubasava Mahaswamiji Institute of Technology",
    "city": "Bagalkot",
    "type": "Private",
    "lat": 16.1719,
    "lng": 75.6996,
    "website": null,
    "nirf_rank": null,
    "affiliation": "VTU"
  },
  {
    "code": "E222",
    "name": "Cambridge Institute Of Technology",
    "city": "Bangalore",
    "type": "Private",
    "lat": 12.9784,
    "lng": 77.589,
    "website": null,
    "nirf_rank": null,
    "affiliation": "VTU"
  },
  {
    "code": "E224",
    "name": "Impact School of Architecture",
    "city": "Bangalore",
    "type": "Private",
    "lat": 12.9722,
    "lng": 77.5928,
    "website": null,
    "nirf_rank": null,
    "affiliation": "VTU"
  },
  {
    "code": "E225",
    "name": "S.J.B School of Architecture and Planning",
    "city": "Bangalore",
    "type": "Private",
    "lat": 12.9738,
    "lng": 77.5858,
    "website": null,
    "nirf_rank": null,
    "affiliation": "VTU"
  },
  {
    "code": "E227",
    "name": "Cauvery institute of Technology",
    "city": "Mandya",
    "type": "Private",
    "lat": 12.5122,
    "lng": 76.8867,
    "website": null,
    "nirf_rank": null,
    "affiliation": "VTU"
  },
  {
    "code": "E228",
    "name": "Mysore School of Architecture Lingabodi",
    "city": "Mysore",
    "type": "Private",
    "lat": 12.295,
    "lng": 76.6338,
    "website": null,
    "nirf_rank": null,
    "affiliation": "VTU"
  },
  {
    "code": "E229",
    "name": "Gopalan School of Architecture and Planning Whitefield",
    "city": "Bangalore",
    "type": "Private",
    "lat": 12.9648,
    "lng": 77.5892,
    "website": null,
    "nirf_rank": null,
    "affiliation": "VTU"
  },
  {
    "code": "E230",
    "name": "R R School of Architecture Chikkabanvara",
    "city": "Bangalore",
    "type": "Private",
    "lat": 12.9768,
    "lng": 77.5866,
    "website": null,
    "nirf_rank": null,
    "affiliation": "VTU"
  },
  {
    "code": "E232",
    "name": "Reva University",
    "city": "Bangalore",
    "type": "Private",
    "lat": 12.9746,
    "lng": 77.596,
    "website": null,
    "nirf_rank": null,
    "affiliation": "VTU"
  },
  {
    "code": "E235",
    "name": "M.S. Ramaiah University of Applied Sciences",
    "city": "Bangalore",
    "type": "Private",
    "lat": 12.9762,
    "lng": 77.6034,
    "website": null,
    "nirf_rank": null,
    "affiliation": "VTU"
  },
  {
    "code": "E237",
    "name": "PRESIDENCY University ITGALPURA",
    "city": "Bangalore",
    "type": "Private",
    "lat": 12.9714,
    "lng": 77.593,
    "website": null,
    "nirf_rank": null,
    "affiliation": "VTU"
  },
  {
    "code": "E238",
    "name": "Mysuru Royal Institute Of Technology",
    "city": "Bangalore",
    "type": "Private",
    "lat": 12.9666,
    "lng": 77.6032,
    "website": null,
    "nirf_rank": null,
    "affiliation": "VTU"
  },
  {
    "code": "E239",
    "name": "East West College Of Engineering",
    "city": "Bangalore",
    "type": "Private",
    "lat": 12.9638,
    "lng": 77.6014,
    "website": null,
    "nirf_rank": null,
    "affiliation": "VTU"
  },
  {
    "code": "E240",
    "name": "Dayananda Sagar University DEVARAKAGGALAHALLI VILLAGE",
    "city": "Ramanagar",
    "type": "Private",
    "lat": 15.3143,
    "lng": 75.7057,
    "website": null,
    "nirf_rank": null,
    "affiliation": "VTU"
  },
  {
    "code": "E241",
    "name": "KLE Technological University(Formerly BVBCET) Dharward Dist",
    "city": "Karnataka",
    "type": "Private",
    "lat": 15.3111,
    "lng": 75.7057,
    "website": null,
    "nirf_rank": null,
    "affiliation": "VTU"
  },
  {
    "code": "E243",
    "name": "Adithya Academy of Architecture and Design Yalahanka",
    "city": "Bangalore",
    "type": "Private",
    "lat": 12.962,
    "lng": 77.5998,
    "website": null,
    "nirf_rank": null,
    "affiliation": "VTU"
  },
  {
    "code": "E244",
    "name": "R V College of Architecture Chikkegowdanapally",
    "city": "Bangalore",
    "type": "Private",
    "lat": 12.9718,
    "lng": 77.601,
    "website": null,
    "nirf_rank": null,
    "affiliation": "VTU"
  },
  {
    "code": "E245",
    "name": "CMR University School of Architecture",
    "city": "Bangalore",
    "type": "Private",
    "lat": 12.9636,
    "lng": 77.595,
    "website": null,
    "nirf_rank": null,
    "affiliation": "VTU"
  },
  {
    "code": "E246",
    "name": "The Oxford School of Architecture",
    "city": "Bangalore",
    "type": "Private",
    "lat": 12.9714,
    "lng": 77.6022,
    "website": null,
    "nirf_rank": null,
    "affiliation": "VTU"
  },
  {
    "code": "E248",
    "name": "Wadiyar Centre For Architecture Mysuru",
    "city": "Mysore",
    "type": "Private",
    "lat": 12.286,
    "lng": 76.6492,
    "website": null,
    "nirf_rank": null,
    "affiliation": "VTU"
  },
  {
    "code": "E250",
    "name": "K S School of Architecture",
    "city": "Bangalore",
    "type": "Private",
    "lat": 12.9676,
    "lng": 77.5956,
    "website": null,
    "nirf_rank": null,
    "affiliation": "VTU"
  },
  {
    "code": "E252",
    "name": "Mysore College of Engineering and Management",
    "city": "Mysore",
    "type": "Private",
    "lat": 12.3,
    "lng": 76.6406,
    "website": null,
    "nirf_rank": null,
    "affiliation": "VTU"
  },
  {
    "code": "E254",
    "name": "A J Institute Of Engineering And Technology.Kottar chowki Boloor Village Mangalore KOTTARA CHOWKI BOLOOR VILLAGE",
    "city": "Mangalore",
    "type": "Private",
    "lat": 12.9183,
    "lng": 74.8608,
    "website": null,
    "nirf_rank": null,
    "affiliation": "VTU"
  },
  {
    "code": "E255",
    "name": "GANDHI INSTITUTE OF TECHNOLOGY AND MANAGEMENT GITAM OFF CAMPUS BENGALURU NH 207",
    "city": "Bangalore",
    "type": "Private",
    "lat": 12.9618,
    "lng": 77.5862,
    "website": null,
    "nirf_rank": null,
    "affiliation": "VTU"
  },
  {
    "code": "E256",
    "name": "RAI TECHNOLOGICAL UNIVERSITY 11TH MILE GALLU",
    "city": "Bangalore",
    "type": "Private",
    "lat": 12.9676,
    "lng": 77.5938,
    "website": null,
    "nirf_rank": null,
    "affiliation": "VTU"
  },
  {
    "code": "E257",
    "name": "CMR University Main Campus",
    "city": "Bangalore",
    "type": "Private",
    "lat": 12.9702,
    "lng": 77.6036,
    "website": null,
    "nirf_rank": null,
    "affiliation": "VTU"
  },
  {
    "code": "E258",
    "name": "Maharaja Institute of Technology THANDAVAPURA",
    "city": "Mysore",
    "type": "Private",
    "lat": 12.2878,
    "lng": 76.6482,
    "website": null,
    "nirf_rank": null,
    "affiliation": "VTU"
  },
  {
    "code": "E259",
    "name": "Sir M V School of Architecture",
    "city": "Bangalore",
    "type": "Private",
    "lat": 12.976,
    "lng": 77.5898,
    "website": null,
    "nirf_rank": null,
    "affiliation": "VTU"
  },
  {
    "code": "E260",
    "name": "Nitte School of Architecture YELAHANKA",
    "city": "Bangalore",
    "type": "Private",
    "lat": 12.9786,
    "lng": 77.5894,
    "website": null,
    "nirf_rank": null,
    "affiliation": "VTU"
  },
  {
    "code": "E261",
    "name": "Angadi School of Architecture BELAGAVI",
    "city": "Belgaum",
    "type": "Private",
    "lat": 15.8595,
    "lng": 74.4915,
    "website": null,
    "nirf_rank": null,
    "affiliation": "VTU"
  },
  {
    "code": "E263",
    "name": "School of Planning and Architecture",
    "city": "Mysore",
    "type": "Private",
    "lat": 12.3052,
    "lng": 76.6458,
    "website": null,
    "nirf_rank": null,
    "affiliation": "VTU"
  },
  {
    "code": "E264",
    "name": "BASAV ENGINEERING SCHOOL OF TECHNOLOGY",
    "city": "Bijapur",
    "type": "Private",
    "lat": 16.8314,
    "lng": 75.7146,
    "website": null,
    "nirf_rank": null,
    "affiliation": "VTU"
  },
  {
    "code": "E265",
    "name": "Jain College of Engineering and Technology",
    "city": "Hubli",
    "type": "Private",
    "lat": 15.3633,
    "lng": 75.1238,
    "website": null,
    "nirf_rank": null,
    "affiliation": "VTU"
  },
  {
    "code": "E266",
    "name": "BMS College of Architecture BMSCE Campus",
    "city": "Bangalore",
    "type": "Private",
    "lat": 12.966,
    "lng": 77.5862,
    "website": null,
    "nirf_rank": null,
    "affiliation": "VTU"
  },
  {
    "code": "E269",
    "name": "Jain College Of Engineering and Research",
    "city": "Belgaum",
    "type": "Private",
    "lat": 15.8441,
    "lng": 74.4959,
    "website": null,
    "nirf_rank": null,
    "affiliation": "VTU"
  },
  {
    "code": "E271",
    "name": "East West School of Architecture Near Anjanagar",
    "city": "Bangalore",
    "type": "Private",
    "lat": 12.972,
    "lng": 77.5936,
    "website": null,
    "nirf_rank": null,
    "affiliation": "VTU"
  },
  {
    "code": "E272",
    "name": "Government Engineering College",
    "city": "Koppal",
    "type": "Government",
    "lat": 15.3536,
    "lng": 76.1462,
    "website": null,
    "nirf_rank": null,
    "affiliation": "VTU"
  },
  {
    "code": "E273",
    "name": "Government Engineering College",
    "city": "Koppal",
    "type": "Government",
    "lat": 15.3558,
    "lng": 76.1508,
    "website": null,
    "nirf_rank": null,
    "affiliation": "VTU"
  },
  {
    "code": "E274",
    "name": "Government Engineering College",
    "city": "Hassan",
    "type": "Government",
    "lat": 12.9973,
    "lng": 76.094,
    "website": null,
    "nirf_rank": null,
    "affiliation": "VTU"
  },
  {
    "code": "E275",
    "name": "R V Institute of Technology and Management JP Nagar",
    "city": "Bangalore",
    "type": "Private",
    "lat": 12.9708,
    "lng": 77.5956,
    "website": null,
    "nirf_rank": null,
    "affiliation": "VTU"
  },
  {
    "code": "E276",
    "name": "Dayananda Sagar College of Architecture",
    "city": "Bangalore",
    "type": "Private",
    "lat": 12.9664,
    "lng": 77.5986,
    "website": null,
    "nirf_rank": null,
    "affiliation": "VTU"
  },
  {
    "code": "E278",
    "name": "VISVESVARAYA TECHNOLOGICAL UNIVERSITY",
    "city": "Belgaum",
    "type": "Private",
    "lat": 15.8423,
    "lng": 74.4895,
    "website": null,
    "nirf_rank": null,
    "affiliation": "VTU"
  },
  {
    "code": "E279",
    "name": "VISVESVARAYA TECHNOLOGICAL UNIVERSITY",
    "city": "Belgaum",
    "type": "Private",
    "lat": 15.8563,
    "lng": 74.4883,
    "website": null,
    "nirf_rank": null,
    "affiliation": "VTU"
  },
  {
    "code": "E280",
    "name": "G S S S School of Architecture for Women",
    "city": "Mysore",
    "type": "Private",
    "lat": 12.2944,
    "lng": 76.6444,
    "website": null,
    "nirf_rank": null,
    "affiliation": "VTU"
  },
  {
    "code": "E281",
    "name": "Government Engineering College",
    "city": "Chitradurga",
    "type": "Government",
    "lat": 15.3183,
    "lng": 75.7219,
    "website": null,
    "nirf_rank": null,
    "affiliation": "VTU"
  },
  {
    "code": "E283",
    "name": "University of Mysuru B.N.BAHADUR INSTITUTE OF MANAGEMENT SCIENCES",
    "city": "Mysore",
    "type": "Private",
    "lat": 12.293,
    "lng": 76.6322,
    "website": null,
    "nirf_rank": null,
    "affiliation": "VTU"
  },
  {
    "code": "E284",
    "name": "Sri Jayachamarajendra College of Engineering(Const. of JSS Univ.)",
    "city": "Mysore",
    "type": "Private",
    "lat": 12.2894,
    "lng": 76.6482,
    "website": null,
    "nirf_rank": null,
    "affiliation": "VTU"
  },
  {
    "code": "E285",
    "name": "R V University",
    "city": "Bangalore",
    "type": "Private",
    "lat": 12.9662,
    "lng": 77.585,
    "website": null,
    "nirf_rank": null,
    "affiliation": "VTU"
  },
  {
    "code": "E286",
    "name": "BGS College of Engineering & Technology",
    "city": "Bangalore",
    "type": "Private",
    "lat": 12.9808,
    "lng": 77.5964,
    "website": null,
    "nirf_rank": null,
    "affiliation": "VTU"
  },
  {
    "code": "E287",
    "name": "Vidyashilp University #125",
    "city": "Bangalore",
    "type": "Private",
    "lat": 12.9648,
    "lng": 77.596,
    "website": null,
    "nirf_rank": null,
    "affiliation": "VTU"
  },
  {
    "code": "E288",
    "name": "Garden City University 16th KM",
    "city": "Karnataka",
    "type": "Private",
    "lat": 15.3089,
    "lng": 75.7163,
    "website": null,
    "nirf_rank": null,
    "affiliation": "VTU"
  },
  {
    "code": "E289",
    "name": "Visvesvaraya Technological University",
    "city": "Karnataka",
    "type": "Private",
    "lat": 15.3099,
    "lng": 75.7171,
    "website": null,
    "nirf_rank": null,
    "affiliation": "VTU"
  },
  {
    "code": "E290",
    "name": "Visvesvaraya Technological University",
    "city": "Mysore",
    "type": "Private",
    "lat": 12.299,
    "lng": 76.6412,
    "website": null,
    "nirf_rank": null,
    "affiliation": "VTU"
  },
  {
    "code": "E291",
    "name": "Government Engineering College",
    "city": "Gadag",
    "type": "Government",
    "lat": 15.4088,
    "lng": 75.627,
    "website": null,
    "nirf_rank": null,
    "affiliation": "VTU"
  },
  {
    "code": "E292",
    "name": "Government Engineering College Bidar",
    "city": "Bidar",
    "type": "Government",
    "lat": 17.9198,
    "lng": 77.5197,
    "website": null,
    "nirf_rank": null,
    "affiliation": "VTU"
  },
  {
    "code": "E293",
    "name": "Poojya Dr.Shivakumar Swamiji School of Architecture Gulbarga",
    "city": "Gulbarga",
    "type": "Private",
    "lat": 17.3261,
    "lng": 76.8331,
    "website": null,
    "nirf_rank": null,
    "affiliation": "VTU"
  },
  {
    "code": "E294",
    "name": "School of Architecture",
    "city": "Mangalore",
    "type": "Private",
    "lat": 12.9069,
    "lng": 74.8548,
    "website": null,
    "nirf_rank": null,
    "affiliation": "VTU"
  },
  {
    "code": "E295",
    "name": "School of Architecture",
    "city": "Belgaum",
    "type": "Private",
    "lat": 15.8579,
    "lng": 74.4995,
    "website": null,
    "nirf_rank": null,
    "affiliation": "VTU"
  },
  {
    "code": "E296",
    "name": "School of Architecture",
    "city": "Tumkur",
    "type": "Private",
    "lat": 13.3397,
    "lng": 77.1131,
    "website": null,
    "nirf_rank": null,
    "affiliation": "VTU"
  },
  {
    "code": "E297",
    "name": "ADITYA COLLEGE OF ENGINEERING AND TECHNOLOGY SURVEY NO 2/8 2/9 AND 2/2",
    "city": "Yelahanka",
    "type": "Private",
    "lat": 15.3181,
    "lng": 75.7045,
    "website": null,
    "nirf_rank": null,
    "affiliation": "VTU"
  },
  {
    "code": "E298",
    "name": "School of Architecture",
    "city": "Bangalore",
    "type": "Private",
    "lat": 12.966,
    "lng": 77.5894,
    "website": null,
    "nirf_rank": null,
    "affiliation": "VTU"
  },
  {
    "code": "E299",
    "name": "Ghousia Institute of Technology for Women",
    "city": "Bangalore",
    "type": "Private",
    "lat": 12.9622,
    "lng": 77.5966,
    "website": null,
    "nirf_rank": null,
    "affiliation": "VTU"
  },
  {
    "code": "E300",
    "name": "AKASH INTITUTE OF ENGINEERING AND TECHNOLOGY PRASANNAHALLI MAIN RAOD",
    "city": "Kasaba",
    "type": "Private",
    "lat": 15.3151,
    "lng": 75.7229,
    "website": null,
    "nirf_rank": null,
    "affiliation": "VTU"
  },
  {
    "code": "E301",
    "name": "KISHKINDA UNIVERSITY BALLARI INSTITUTE OF TECHNOLOGY & MANAGEMENT",
    "city": "Karnataka",
    "type": "Private",
    "lat": 15.3105,
    "lng": 75.7233,
    "website": null,
    "nirf_rank": null,
    "affiliation": "VTU"
  },
  {
    "code": "E302",
    "name": "AMITY UNIVERSITY National Highway 648",
    "city": "Karnataka",
    "type": "Private",
    "lat": 15.3263,
    "lng": 75.7115,
    "website": null,
    "nirf_rank": null,
    "affiliation": "VTU"
  },
  {
    "code": "E303",
    "name": "GM University KARUR VILLAGE",
    "city": "Davangere",
    "type": "Private",
    "lat": 15.3113,
    "lng": 75.7129,
    "website": null,
    "nirf_rank": null,
    "affiliation": "VTU"
  },
  {
    "code": "E304",
    "name": "ANUVARTIK MIRJI BHARATESH INSTITUTE OF TECHNOLOGY BELAGAVI",
    "city": "Belgaum",
    "type": "Private",
    "lat": 15.8419,
    "lng": 74.4997,
    "website": null,
    "nirf_rank": null,
    "affiliation": "VTU"
  },
  {
    "code": "E305",
    "name": "DR H N NATIONAL COLLEGE OF ENGINEERING BENGALURU",
    "city": "Bangalore",
    "type": "Private",
    "lat": 12.978,
    "lng": 77.604,
    "website": null,
    "nirf_rank": null,
    "affiliation": "VTU"
  },
  {
    "code": "E306",
    "name": "THE CHANAKYA UNIVERSITY NO 29 HARALURU",
    "city": "Devanahalli",
    "type": "Private",
    "lat": 15.3165,
    "lng": 75.7179,
    "website": null,
    "nirf_rank": null,
    "affiliation": "VTU"
  },
  {
    "code": "E307",
    "name": "SESHADRIPURAM INSTITUTE OF TECHNOLOGY MYSURU MYSURU",
    "city": "Mysore",
    "type": "Private",
    "lat": 12.2922,
    "lng": 76.6406,
    "website": null,
    "nirf_rank": null,
    "affiliation": "VTU"
  },
  {
    "code": "E308",
    "name": "CONSTITUENT COLLEGE OF VTU",
    "city": "Chintamani",
    "type": "Private",
    "lat": 15.3207,
    "lng": 75.7099,
    "website": null,
    "nirf_rank": null,
    "affiliation": "VTU"
  },
  {
    "code": "E309",
    "name": "CONSTITUENT COLLEGE OF VTU",
    "city": "Chintamani",
    "type": "Private",
    "lat": 15.3111,
    "lng": 75.7081,
    "website": null,
    "nirf_rank": null,
    "affiliation": "VTU"
  },
  {
    "code": "E310",
    "name": "GOVERNMENT ENGINEERING COLLEGE",
    "city": "Hassan",
    "type": "Government",
    "lat": 13.0055,
    "lng": 76.0988,
    "website": null,
    "nirf_rank": null,
    "affiliation": "VTU"
  },
  {
    "code": "E311",
    "name": "RATHINAM INSTITUTE OF TECHNOLOGY DODDAKAMMANAHALLY VILLAGE",
    "city": "Begur",
    "type": "Private",
    "lat": 15.3177,
    "lng": 75.7051,
    "website": null,
    "nirf_rank": null,
    "affiliation": "VTU"
  },
  {
    "code": "E312",
    "name": "NEW EBENEZER INSTITUTE OF TECHNOLOGY HENNUR BAGALUR MAIN ROAD",
    "city": "Kothnur",
    "type": "Private",
    "lat": 15.3269,
    "lng": 75.7141,
    "website": null,
    "nirf_rank": null,
    "affiliation": "VTU"
  },
  {
    "code": "E313",
    "name": "HARSHA INSTITUTE OF TECHNOLOGY VARADANAYAKANA HALLY VILLAGE",
    "city": "Nelamangala",
    "type": "Private",
    "lat": 15.3121,
    "lng": 75.7083,
    "website": null,
    "nirf_rank": null,
    "affiliation": "VTU"
  },
  {
    "code": "E314",
    "name": "CAUVERY COLLEGE OF ENGINEERING KBL LAYOUT",
    "city": "Mysore",
    "type": "Private",
    "lat": 12.297,
    "lng": 76.6432,
    "website": null,
    "nirf_rank": null,
    "affiliation": "VTU"
  },
  {
    "code": "E315",
    "name": "VTU CONSTITUENT ENGINEERING COLLEGE - GOKAK",
    "city": "Karnataka",
    "type": "Private",
    "lat": 15.3079,
    "lng": 75.7179,
    "website": null,
    "nirf_rank": null,
    "affiliation": "VTU"
  }
]